lunasvg-0.0.9.dist-info/METADATA
lunasvg-0.0.9.dist-info/WHEEL
lunasvg-0.0.9.dist-info/LICENSE
lunasvg/_lunasvg.cp38-win_amd64.pyd
lunasvg/_lunasvg.cp38-win_amd64.lib
lunasvg/__init__.py
lunasvg/__init__.pyi
lunasvg/__main__.py
lunasvg/py.typed
lunasvg-0.0.9.dist-info/RECORD
