Metadata-Version: 2.1
Name: lunasvg
Version: 0.0.9
Summary: SVG rendering library
Keywords: svg,png,svg2png
Home-page: https://github.com/sammycage/lunasvg
Author-Email: Samuel Ugochukwu <sammycageagle@gmail.com>
License: MIT License
Classifier: Development Status :: 4 - Beta
Classifier: Intended Audience :: Developers
Classifier: License :: OSI Approved :: MIT License
Classifier: Operating System :: OS Independent
Classifier: Programming Language :: Python :: 3.8
Classifier: Programming Language :: Python :: 3.9
Classifier: Programming Language :: Python :: 3.10
Classifier: Programming Language :: Python :: 3.11
Classifier: Programming Language :: Python :: 3.12
Classifier: Programming Language :: Python :: Implementation :: CPython
Classifier: Programming Language :: Python :: Implementation :: PyPy
Classifier: Topic :: Multimedia :: Graphics :: Graphics Conversion
Classifier: Topic :: Multimedia :: Graphics :: Presentation
Classifier: Topic :: Text Processing :: Markup :: XML
Project-URL: Homepage, https://github.com/sammycage/lunasvg
Project-URL: Code, https://github.com/sammycage/lunasvg-python
Project-URL: Issues, https://github.com/sammycage/lunasvg-python/issues
Project-URL: Donation, https://www.paypal.com/paypalme/sammycage
Requires-Python: >=3.8
